QHyper/__init__.py
QHyper/util.py
QHyper/hyperparameter_gen/__init__.py
QHyper/hyperparameter_gen/parser.py
QHyper/optimizers/__init__.py
QHyper/optimizers/base.py
QHyper/optimizers/basinhopping.py
QHyper/optimizers/cem.py
QHyper/optimizers/qml_gradient_descent.py
QHyper/optimizers/random.py
QHyper/optimizers/scipy_minimizer.py
QHyper/problems/__init__.py
QHyper/problems/base.py
QHyper/problems/community_detection.py
QHyper/problems/knapsack.py
QHyper/problems/maxcut.py
QHyper/problems/tsp.py
QHyper/problems/workflow_scheduling.py
QHyper/solvers/__init__.py
QHyper/solvers/base.py
QHyper/solvers/converter.py
QHyper/solvers/cqm/__init__.py
QHyper/solvers/cqm/cqm.py
QHyper/solvers/dqm/__init__.py
QHyper/solvers/dqm/dqm.py
QHyper/solvers/gurobi/__init__.py
QHyper/solvers/gurobi/gurobi.py
QHyper/solvers/vqa/__init__.py
QHyper/solvers/vqa/base.py
QHyper/solvers/vqa/eval_funcs/__init__.py
QHyper/solvers/vqa/eval_funcs/base.py
QHyper/solvers/vqa/eval_funcs/wfeval.py
QHyper/solvers/vqa/pqc/__init__.py
QHyper/solvers/vqa/pqc/base.py
QHyper/solvers/vqa/pqc/h_qaoa.py
QHyper/solvers/vqa/pqc/mixers.py
QHyper/solvers/vqa/pqc/qaoa.py
QHyper/solvers/vqa/pqc/wf_qaoa.py
qhyper-1.0.0.dist-info/LICENSE.txt
qhyper-1.0.0.dist-info/METADATA
qhyper-1.0.0.dist-info/WHEEL
qhyper-1.0.0.dist-info/top_level.txt
qhyper-1.0.0.dist-info/RECORD
